sap-cloud-connector-python-socket/__init__.py
sap-cloud-connector-python-socket/sap-cloud-connector-python-socket.py
sapcloudconnectorpythonsocket/__init__.py
sapcloudconnectorpythonsocket/sapcloudconnectorpythonsocket.py
sapcloudconnectorpythonsocket-0.1.4.dist-info/LICENSE
sapcloudconnectorpythonsocket-0.1.4.dist-info/METADATA
sapcloudconnectorpythonsocket-0.1.4.dist-info/WHEEL
sapcloudconnectorpythonsocket-0.1.4.dist-info/top_level.txt
sapcloudconnectorpythonsocket-0.1.4.dist-info/RECORD
